nautacli/__about__.py
nautacli/__init__.py
nautacli/nauta.py
nauta_cli-0.7.1.dist-info/LICENSE
nauta_cli-0.7.1.dist-info/METADATA
nauta_cli-0.7.1.dist-info/WHEEL
nauta_cli-0.7.1.dist-info/entry_points.txt
nauta_cli-0.7.1.dist-info/top_level.txt
nauta_cli-0.7.1.dist-info/RECORD
