Metadata-Version: 2.1
Name: nauta-cli
Version: 0.7.1
Summary: Utilidad en linea de comandos (CLI) para la gestion del portal cautivo Nauta de Cuba
Home-page: https://github.com/abrahamtoledo/nauta-cli
Author: Abraham Toledo Sanchez
Author-email: abrahamtoledo90@gmail.com
License: UNKNOWN
Keywords: nauta portal cautivo
Platform: UNKNOWN
Classifier: Development Status :: 3 - Alpha
Classifier: Intended Audience :: End Users/Desktop
Classifier: Topic :: Internet
Classifier: License :: OSI Approved :: MIT License
Classifier: Programming Language :: Python
Requires-Dist: requests
Requires-Dist: bs4
